geocr/__init__.py
geocr/archive_collection.py
geocr/archive_geolocator.py
geocr/archive_image.py
geocr/geo_exporter.py
geocr-1.1.0.dist-info/licenses/LICENSE
geocr-1.1.0.dist-info/METADATA
geocr-1.1.0.dist-info/WHEEL
geocr-1.1.0.dist-info/top_level.txt
geocr-1.1.0.dist-info/RECORD
