Metadata-Version: 2.4
Name: geocr
Version: 1.1.0
Summary: GeOCR is a Python library for OCR, data cleaning, and historical geocoding using custom GeoJSON maps.
Author: Joshua Vachon
License: MIT
Requires-Python: >=3.9
License-File: LICENSE
Requires-Dist: opencv-python-headless<5.0,>=4.11
Requires-Dist: numpy<3.0,>=2.0
Requires-Dist: matplotlib<4.0,>=3.10
Requires-Dist: pytesseract<1.0,>=0.3
Requires-Dist: pillow<12.0,>=11.2
Requires-Dist: ipython<9.0,>=7.34
Requires-Dist: pandas<3.0,>=2.2
Requires-Dist: geopandas<2.0,>=1.0
Requires-Dist: shapely<3.0,>=2.1
Requires-Dist: rapidfuzz<4.0,>=3.13
Dynamic: license-file
